image_interlacement-1.2.0.dist-info/licenses/LICENSE
src/__init__.py
src/composite.py
src/main.py
image_interlacement-1.2.0.dist-info/METADATA
image_interlacement-1.2.0.dist-info/WHEEL
image_interlacement-1.2.0.dist-info/entry_points.txt
image_interlacement-1.2.0.dist-info/top_level.txt
image_interlacement-1.2.0.dist-info/RECORD
