Metadata-Version: 2.4
Name: image-interlacement
Version: 1.2.0
Summary: CLI tool for creating composites by alternating rows/columns from two images
Author-email: "e. couture" <your.email@example.com>
License: GPLv3
Project-URL: Homepage, https://github.com/yourusername/image-interlacement
Project-URL: Repository, https://github.com/yourusername/image-interlacement.git
Project-URL: Issues, https://github.com/yourusername/image-interlacement/issues
Keywords: image,composite,interlace,interleave,CLI
Classifier: Development Status :: 4 - Beta
Classifier: Environment :: Console
Classifier: Intended Audience :: End Users/Desktop
Classifier: License :: OSI Approved :: MIT License
Classifier: Natural Language :: English
Classifier: Operating System :: OS Independent
Classifier: Programming Language :: Python :: 3
Classifier: Programming Language :: Python :: 3.8
Classifier: Programming Language :: Python :: 3.9
Classifier: Programming Language :: Python :: 3.10
Classifier: Programming Language :: Python :: 3.11
Classifier: Programming Language :: Python :: 3.12
Classifier: Programming Language :: Python :: 3.13
Classifier: Topic :: Multimedia :: Graphics
Classifier: Topic :: Utilities
Requires-Python: >=3.8
License-File: LICENSE
Requires-Dist: Pillow>=9.0.0
Requires-Dist: numpy>=1.21.0
Provides-Extra: dev
Requires-Dist: pytest>=7.0; extra == "dev"
Requires-Dist: pytest-cov>=3.0; extra == "dev"
Requires-Dist: black>=22.0; extra == "dev"
Requires-Dist: flake8>=4.0; extra == "dev"
Provides-Extra: build
Requires-Dist: pyinstaller>=6.0; extra == "build"
Dynamic: license-file
